cereon_sdk/__init__.py
cereon_sdk/protocols.py
cereon_sdk/routes.py
cereon_sdk/types.py
cereon_sdk/utils.py
cereon_sdk-0.1.5.dist-info/METADATA
cereon_sdk-0.1.5.dist-info/WHEEL
cereon_sdk-0.1.5.dist-info/licenses/LICENSE
cereon_sdk-0.1.5.dist-info/RECORD
