Metadata-Version: 2.4
Name: cereon_sdk
Version: 0.1.5
Summary: Generic, typed, and streaming FastAPI backend for Cereon Dashboard cards.
Project-URL: Homepage, https://github.com/adimis-ai/cereon-sdk
Project-URL: Repository, https://github.com/adimis-ai/cereon-sdk
Project-URL: Issues, https://github.com/adimis-ai/cereon-sdk/issues
Author-email: Aditya Mishra <adimis.sde@gmail.com>
License: MIT License
License-File: LICENSE
Keywords: dashboard,fastapi,ndjson,sse,streaming,typed-api,websocket
Classifier: Framework :: FastAPI
Classifier: License :: OSI Approved :: MIT License
Classifier: Operating System :: OS Independent
Classifier: Programming Language :: Python :: 3
Requires-Python: >=3.10
Requires-Dist: fastapi>=0.110.0
Requires-Dist: pydantic>=2.6.0
Requires-Dist: typing-extensions>=4.9.0
Provides-Extra: dev
Requires-Dist: black; extra == 'dev'
Requires-Dist: pytest; extra == 'dev'
Requires-Dist: pytest-asyncio; extra == 'dev'
Requires-Dist: ruff; extra == 'dev'
